acceso_solana/__init__.py
acceso_solana/client.py
acceso_solana/types.py
acceso_solana-1.0.0.dist-info/licenses/LICENSE
acceso_solana-1.0.0.dist-info/METADATA
acceso_solana-1.0.0.dist-info/WHEEL
acceso_solana-1.0.0.dist-info/top_level.txt
acceso_solana-1.0.0.dist-info/RECORD
