Metadata-Version: 2.4
Name: acceso-solana
Version: 1.0.0
Summary: Python SDK for Acceso Solana API - Complete Solana blockchain operations
Author-email: Acceso <dev@acceso.dev>
License: MIT
Project-URL: Homepage, https://acceso.dev
Project-URL: Documentation, https://docs.acceso.dev
Project-URL: Repository, https://github.com/acceso-dev/acceso-solana-python
Keywords: acceso,solana,blockchain,crypto,web3,nft,defi,spl,jupiter
Classifier: Development Status :: 5 - Production/Stable
Classifier: Intended Audience :: Developers
Classifier: Operating System :: OS Independent
Classifier: Programming Language :: Python :: 3
Classifier: Programming Language :: Python :: 3.8
Classifier: Programming Language :: Python :: 3.9
Classifier: Programming Language :: Python :: 3.10
Classifier: Programming Language :: Python :: 3.11
Classifier: Programming Language :: Python :: 3.12
Classifier: Topic :: Software Development :: Libraries :: Python Modules
Classifier: Topic :: Office/Business :: Financial :: Investment
Requires-Python: >=3.8
License-File: LICENSE
Requires-Dist: requests>=2.25.0
Provides-Extra: dev
Requires-Dist: pytest>=7.0.0; extra == "dev"
Requires-Dist: pytest-cov>=4.0.0; extra == "dev"
Requires-Dist: black>=23.0.0; extra == "dev"
Requires-Dist: mypy>=1.0.0; extra == "dev"
Requires-Dist: types-requests>=2.28.0; extra == "dev"
Dynamic: license-file
